debug/__init__.py
py3_debug-0.0.1.dist-info/licenses/LICENSE
py3_debug-0.0.1.dist-info/METADATA
py3_debug-0.0.1.dist-info/WHEEL
py3_debug-0.0.1.dist-info/top_level.txt
py3_debug-0.0.1.dist-info/RECORD
