Metadata-Version: 2.4
Name: py3-debug
Version: 0.0.1
Summary: py3-debug 是一款开源辅助 debug 工具注解库，可帮助重新生成类方法调用信息。
Author-email: Talbot3 <1796560392@qq.com>
Project-URL: Homepage, https://github.com/Talbot3/py3-debug
Project-URL: Issues, https://github.com/Talbot3/py3-debug/issues
Classifier: Programming Language :: Python :: 3
Classifier: License :: OSI Approved :: MIT License
Classifier: Operating System :: OS Independent
License-File: LICENSE
Dynamic: license-file
